tuzi_mcp/__init__.py
tuzi_mcp/gemini_client.py
tuzi_mcp/gpt_client.py
tuzi_mcp/image_utils.py
tuzi_mcp/seedream_client.py
tuzi_mcp/server.py
tuzi_mcp/task_manager.py
tuzi_mcp-0.3.3.dist-info/METADATA
tuzi_mcp-0.3.3.dist-info/WHEEL
tuzi_mcp-0.3.3.dist-info/entry_points.txt
tuzi_mcp-0.3.3.dist-info/top_level.txt
tuzi_mcp-0.3.3.dist-info/RECORD
