Metadata-Version: 2.4
Name: tuzi-mcp
Version: 0.3.3
Summary: An MCP (Model Context Protocol) server for asynchronous image generation using the Tu-zi API
Requires-Python: >=3.13
Requires-Dist: fastmcp>=2.11.3
Requires-Dist: httpx>=0.28.1
